LICENSE
MANIFEST.in
README.md
setup.py
wasic/__init__.py
wasic/constants.py
wasic/sdk.py
wasic/tools.py
wasic/wasiar.py
wasic/wasic.cmake
wasic/wasic.py
wasic/wasicc.py
wasic/wasiconfigure.py
wasic/wasild.py
wasic/wasimake.py
wasic/wasinm.py
wasic/wasiranlib.py
wasic/wasirun.py
wasic.egg-info/PKG-INFO
wasic.egg-info/SOURCES.txt
wasic.egg-info/dependency_links.txt
wasic.egg-info/entry_points.txt
wasic.egg-info/not-zip-safe
wasic.egg-info/top_level.txt
wasic/stubs/dirent.h
wasic/stubs/dlfcn.h
wasic/stubs/grp.h
wasic/stubs/netdb.h
wasic/stubs/preamble.h
wasic/stubs/pthread.h
wasic/stubs/pty.h
wasic/stubs/pwd.h
wasic/stubs/termios.h
wasic/stubs/bits/ioctl.h
wasic/stubs/bits/termios.h
wasic/stubs/net/if.h
wasic/stubs/netinet/in.h
wasic/stubs/sys/ioctl.h
wasic/stubs/sys/statvfs.h
wasic/stubs/sys/wait.h
wasic/stubs/sys/xattr.h